gns3/__init__.py
gns3/__main__.py
gns3/appliance_manager.py
gns3/application.py
gns3/base_node.py
gns3/compute.py
gns3/compute_manager.py
gns3/compute_summary_view.py
gns3/console_cmd.py
gns3/console_view.py
gns3/controller.py
gns3/crash_report.py
gns3/graphics_view.py
gns3/http_client.py
gns3/http_client_error.py
gns3/image_manager.py
gns3/image_upload_manager.py
gns3/link.py
gns3/local_config.py
gns3/local_server.py
gns3/logger.py
gns3/main.py
gns3/main_window.py
gns3/network_client.py
gns3/node.py
gns3/nodes_dock_widget.py
gns3/nodes_view.py
gns3/packet_capture.py
gns3/progress.py
gns3/project.py
gns3/pycutext.py
gns3/settings.py
gns3/spice_console.py
gns3/status_bar.py
gns3/style.py
gns3/symbol.py
gns3/telnet_console.py
gns3/template.py
gns3/template_manager.py
gns3/topology.py
gns3/topology_summary_view.py
gns3/update_manager.py
gns3/version.py
gns3/vnc_console.py
gns3/dialogs/__init__.py
gns3/dialogs/about_dialog.py
gns3/dialogs/appliance_wizard.py
gns3/dialogs/capture_dialog.py
gns3/dialogs/configuration_dialog.py
gns3/dialogs/console_command_dialog.py
gns3/dialogs/custom_adapters_configuration_dialog.py
gns3/dialogs/doctor_dialog.py
gns3/dialogs/edit_compute_dialog.py
gns3/dialogs/edit_project_dialog.py
gns3/dialogs/exec_command_dialog.py
gns3/dialogs/export_debug_dialog.py
gns3/dialogs/file_editor_dialog.py
gns3/dialogs/filter_dialog.py
gns3/dialogs/idlepc_dialog.py
gns3/dialogs/image_dialog.py
gns3/dialogs/login_dialog.py
gns3/dialogs/new_template_wizard.py
gns3/dialogs/node_info_dialog.py
gns3/dialogs/node_properties_dialog.py
gns3/dialogs/notif_dialog.py
gns3/dialogs/password_dialog.py
gns3/dialogs/preferences_dialog.py
gns3/dialogs/profile_select.py
gns3/dialogs/project_dialog.py
gns3/dialogs/project_export_wizard.py
gns3/dialogs/project_welcome_dialog.py
gns3/dialogs/setup_wizard.py
gns3/dialogs/show_readme_dialog.py
gns3/dialogs/snapshots_dialog.py
gns3/dialogs/style_editor_dialog.py
gns3/dialogs/style_editor_dialog_link.py
gns3_gui-3.0.5.dist-info/licenses/LICENSE
gns3_gui-3.0.5.dist-info/METADATA
gns3_gui-3.0.5.dist-info/WHEEL
gns3_gui-3.0.5.dist-info/entry_points.txt
gns3_gui-3.0.5.dist-info/top_level.txt
gns3_gui-3.0.5.dist-info/RECORD
