Metadata-Version: 2.4
Name: gns3-gui
Version: 3.0.5
Summary: GNS3 graphical interface for the GNS3 server.
Author-email: Jeremy Grossmann <developers@gns3.com>
Project-URL: Homepage, http://gns3.com
Project-URL: Repository, http://github.com/GNS3/gns3-gui
Project-URL: Bug tracker, http://github.com/GNS3/gns3-gui/issues
Classifier: Development Status :: 5 - Production/Stable
Classifier: Environment :: X11 Applications :: Qt
Classifier: Intended Audience :: Information Technology
Classifier: Topic :: System :: Networking
Classifier: License :: OSI Approved :: GNU General Public License v3 (GPLv3)
Classifier: Natural Language :: English
Classifier: Operating System :: POSIX
Classifier: Operating System :: MacOS :: MacOS X
Classifier: Operating System :: Microsoft :: Windows
Classifier: Programming Language :: Python :: 3 :: Only
Classifier: Programming Language :: Python :: 3.9
Classifier: Programming Language :: Python :: 3.10
Classifier: Programming Language :: Python :: 3.11
Classifier: Programming Language :: Python :: 3.12
Classifier: Programming Language :: Python :: 3.13
Classifier: Programming Language :: Python :: Implementation :: CPython
Requires-Python: >=3.9
License-File: LICENSE
Requires-Dist: jsonschema<4.24,>=4.23
Requires-Dist: sentry-sdk<2.27,>=2.26.1
Requires-Dist: psutil>=7.0.0
Requires-Dist: distro>=1.9.0
Requires-Dist: truststore>=0.10.1; python_version >= "3.10"
Requires-Dist: importlib-resources>=1.3; python_version < "3.9"
Provides-Extra: dev
Requires-Dist: pytest==8.3.4; extra == "dev"
Requires-Dist: pytest-timeout==2.3.1; extra == "dev"
Dynamic: license-file
